keepass2_merger/__init__.py
keepass2_merger/__main__.py
keepass2_merger/cli.py
keepass2_merger-0.0.2.dist-info/licenses/LICENSE
keepass2_merger-0.0.2.dist-info/METADATA
keepass2_merger-0.0.2.dist-info/WHEEL
keepass2_merger-0.0.2.dist-info/entry_points.txt
keepass2_merger-0.0.2.dist-info/top_level.txt
keepass2_merger-0.0.2.dist-info/RECORD
