Metadata-Version: 2.4
Name: keepass2-merger
Version: 0.0.2
Summary: A python package to interactively merge two KeePass2 databases.
Author-email: Karol Gotkowski <KarolGotkowski@gmx.de>
License: MIT
Project-URL: Homepage, https://github.com/Karol-G/keepass2-merger
Project-URL: Source, https://github.com/Karol-G/keepass2-merger
Project-URL: Issues, https://github.com/Karol-G/keepass2-merger/issues
Keywords: copier,template,python
Classifier: Programming Language :: Python :: 3
Classifier: Programming Language :: Python :: 3.9
Classifier: Operating System :: OS Independent
Requires-Python: >=3.9
License-File: LICENSE
Requires-Dist: pykeepass>=4.0.3
Provides-Extra: dev
Requires-Dist: build>=1.0; extra == "dev"
Requires-Dist: pytest>=7.0; extra == "dev"
Requires-Dist: twine>=4.0; extra == "dev"
Requires-Dist: setuptools_scm[toml]>=8.0; extra == "dev"
Dynamic: license-file
